uscrn/__init__.py
uscrn/_util.py
uscrn/attrs.py
uscrn/attrs.yml
uscrn/data.py
uscrn/py.typed
uscrn-0.2.0.dist-info/LICENSE
uscrn-0.2.0.dist-info/WHEEL
uscrn-0.2.0.dist-info/METADATA
uscrn-0.2.0.dist-info/RECORD
