Metadata-Version: 2.1
Name: uscrn
Version: 0.2.0
Summary: Load `U.S. Climate Reference Network <https://www.ncei.noaa.gov/access/crn/>`__ (USCRN) data.
Author-email: zmoon <zachary.moon@noaa.gov>
Requires-Python: ~=3.9
Classifier: License :: OSI Approved :: MIT License
Requires-Dist: joblib
Requires-Dist: numpy >=1.21
Requires-Dist: pandas >=2,<3
Requires-Dist: PyYAML
Requires-Dist: requests
Requires-Dist: xarray
Requires-Dist: ipython ; extra == "dev"
Requires-Dist: jupyterlab ; extra == "doc"
Requires-Dist: matplotlib ; extra == "doc"
Requires-Dist: myst-nb ; extra == "doc"
Requires-Dist: myst-parser ; extra == "doc"
Requires-Dist: sphinx ; extra == "doc"
Requires-Dist: sphinx-book-theme ; extra == "doc"
Requires-Dist: sphinx-click ; extra == "doc"
Requires-Dist: sphinx-copybutton ; extra == "doc"
Requires-Dist: fastparquet ; extra == "test"
Requires-Dist: mypy ; extra == "test"
Requires-Dist: netCDF4 ; extra == "test"
Requires-Dist: pandas-stubs ; extra == "test"
Requires-Dist: pyarrow ; extra == "test"
Requires-Dist: pytest ; extra == "test"
Requires-Dist: pytest-cov ; extra == "test"
Project-URL: Documentation, https://uscrn.readthedocs.io
Project-URL: Home, https://github.com/zmoon/uscrn
Project-URL: Source, https://github.com/zmoon/uscrn
Provides-Extra: dev
Provides-Extra: doc
Provides-Extra: test
